pytoolkit_solunegocios/__init__.py
pytoolkit_solunegocios/azure/__init__.py
pytoolkit_solunegocios/azure/ai_search.py
pytoolkit_solunegocios/azure/open_ai.py
pytoolkit_solunegocios/azure/azure_auth/__init__.py
pytoolkit_solunegocios/azure/azure_auth/auth.py
pytoolkit_solunegocios/azure/azure_auth/config.py
pytoolkit_solunegocios-0.0.3.dist-info/LICENSE
pytoolkit_solunegocios-0.0.3.dist-info/METADATA
pytoolkit_solunegocios-0.0.3.dist-info/WHEEL
pytoolkit_solunegocios-0.0.3.dist-info/top_level.txt
pytoolkit_solunegocios-0.0.3.dist-info/RECORD
