Metadata-Version: 2.1
Name: pytoolkit_solunegocios
Version: 0.0.3
Home-page: 
Author: Cristian Pavez
Author-email: cpavezm@soluciones.cl
Requires-Python: >=3.6
License-File: LICENSE
Requires-Dist: azure-search-documents==11.5.1
Requires-Dist: azure-core==1.30.2
Requires-Dist: openai==1.43.1
Requires-Dist: msal==1.20.0
Requires-Dist: requests>=2.25.1
Provides-Extra: dev
Requires-Dist: pytest>=6.0; extra == "dev"
Requires-Dist: black; extra == "dev"
Requires-Dist: flake8; extra == "dev"
